README.md
setup.cfg
setup.py
blaze_distributions/Binomialdistribution.py
blaze_distributions/Gaussiandistribution.py
blaze_distributions/Generaldistribution.py
blaze_distributions/__init__.py
blaze_distributions.egg-info/PKG-INFO
blaze_distributions.egg-info/SOURCES.txt
blaze_distributions.egg-info/dependency_links.txt
blaze_distributions.egg-info/not-zip-safe
blaze_distributions.egg-info/top_level.txt