Metadata-Version: 1.0
Name: blaze-distributions
Version: 0.1
Summary: Gaussian and Binomial distributions
Home-page: UNKNOWN
Author: Toluwalope Oluyipe
Author-email: kingtoluwalope@gmail.com
License: UNKNOWN
Platform: UNKNOWN
